{"detail": "米豆腐是我们老家的特色美食，尤其是老一辈的，都喜欢吃，妈妈喜欢用米豆腐做早餐，可我总觉得米豆腐一点都不入味，后来把米豆腐切成小小的块，搭配点剁辣椒，辣辣的吃得很舒服呢。", "taste": "香辣味", "features": "", "image": "http://site.meishij.net/r/208/102/1025708/s1025708_146149738925092.jpg", "labels": ["热菜", "江西小吃", "家常菜", "午餐"], "name": "#湘西小吃#菜沫米豆腐", "method": "煮", "image_name": "test_images/2236_s1025708_146149738925092.jpg"}
{"detail": "牛肉米粉绝对是我们当地最受欢迎的早餐，一般要到外面的粉馆才能吃到，但是粉馆里面的各种调料里少不了添加剂之类的，所以我们来自己动手为家人做这个健康又美味的牛肉米粉吧！", "taste": "其它口味", "features": "", "image": "http://site.meishij.net/r/21/124/5718521/s5718521_145860801129365.jpg", "labels": ["糕点主食", "江西小吃", "午餐"], "name": "南充牛肉米粉", "method": "其它工艺", "image_name": "test_images/2328_s5718521_145860801129365.jpg"}
{"detail": "在南充街头总有叫卖“热凉粉”的小贩，味道各一。儿时在老家也曾和家人一起做来吃过，如今远离故土，却难以找到熟悉的味道了。于是一时兴起便做来尝试，竟被自己做的惊艳到了，好吃到哭啊！！（此处应有掌声~）本想着独留秘方，绝不外传，要是哪天失业了混口倒饭吃。。想了想倒也罢了，还是大家齐分享吧！", "taste": "香辣味", "features": "", "image": "http://site.meishij.net/r/197/203/4363447/s4363447_145188495995641.jpg", "labels": ["热菜", "江西小吃", "家常菜", "午餐"], "name": "老南充热凉粉", "method": "煮", "image_name": "test_images/2371_s4363447_145188495995641.jpg"}
{"detail": "说到南昌美食，所有南昌人首先都会推荐南昌凉拌粉。南昌人的早餐经典凉拌粉具有“韧、爽、鲜、滑”的特点，由于米粉本身筋道，再加上煮熟后马上入水冷却，使得米粉丝毫不绵软，韧性十足，过水滤干能保证米粉吃起来根根清楚、条条滑溜，再加上佐料拌起来，南昌凉拌粉开胃爽口，即便是严严夏日也令人食欲大动。", "taste": "香辣味", "features": "", "image": "http://site.meishij.net/r/208/36/1259208/s1259208_59032.jpg", "labels": ["糕点主食", "江西小吃"], "name": "南昌凉拌粉", "method": "煮", "image_name": "test_images/2653_s1259208_59032.jpg"}
