{"features": "", "labels": ["热菜", "老年人", "西餐面点", "午餐"], "taste": "奶香味", "detail": "墨西哥酱料配上烤土豆，不只是健康这么简单了，是的，土豆不是最好的东西，但这些烤土豆淋上红色的拉达调味酱，是不是让你感觉很棒呢。", "image": "http://site.meishij.net/r/145/221/6930395/s6930395_147470215826446.jpg", "method": "烤", "name": "芝士烤土豆"}
{"features": ["防癌", "抗衰老", "保护血管", "美容瘦身", "美容养颜", "益智安神", "消除水肿", "延缓衰老", "抵抗力", "降糖", "保护视力", "助消化", "消食", "降血压", "补钙", "延年益寿", "健脑益智", "保肝", "动脉硬化", "美容护肤", "中毒", "糖尿病", "减肥", "健脑"], "labels": ["东北菜", "老年人", "素食", "主食"], "taste": "咸鲜味", "detail": "以前上学时，学校的食堂的超好吃，就是卤太咸了。哈哈，东北有点口重。毕业回家了就吃不到了。那就自己动手吧", "image": "http://site.meishij.net/r/60/19/10442310/s10442310_151063761373195.jpg", "method": "炒", "name": "自制家庭美味茄子打卤面"}
{"features": "", "labels": ["热菜", "湖北菜", "孕妇", "产妇", "老年人", "家常菜", "午餐", "晚餐"], "taste": "家常味", "detail": "莲藕排骨汤，汉族名菜，属鄂菜系。作为千湖之省、水乡泽国和莲藕之乡的湖北名菜。在湖北，素有“无汤不成席”的说法，举凡筵宴，压轴戏必然是一罐鲜醇香美的汤。莲藕排骨汤不但有润肠道，清热消痰、补血养颜的功效，而且还能够有效的健脾胃，是适合经常食用。", "image": "http://site.meishij.net/r/139/39/5447389/s5447389_146365692140993.jpg", "method": "蒸", "name": "莲藕蒸排骨"}
{"features": "", "labels": ["热菜", "粤菜", "老年人", "私家菜", "晚餐"], "taste": "咸鲜味", "detail": "在广东的朋友相信都知道油榄角是什么东东的哈，经常会用它来蒸鱼，蒸排骨，味道清香四溢，开胃醒神，其实油榄角是由乌橄榄腌制而成的。乌橄榄在成熟时，皮是乌黑色的，里面的肉是黄色的，也有紫红色的。最好的乌橄榄叫油榄，比较香。把乌橄榄放入开水烫软，然后把它的肉和核分开，榄肉用盐腌起来，就成了咸榄角。榄核晒干后，用小锤子敲开，肉里的肉可是比橄榄肉还香。", "image": "http://site.meishij.net/r/72/122/2343072/s2343072_00145.jpg", "method": "蒸", "name": "油榄角蒸鲈鱼"}
{"features": ["清热解暑", "开胃健脾", "抵抗力", "抵抗力", "养肾", "消食"], "labels": ["苏菜", "老年人", "家常菜"], "taste": "咸鲜味", "detail": "今天这菜充分证明了俺某一方面的人生哲学，那就是——自做孽不可活！从何说起呢？", "image": "http://images.meishij.net/p/20141125/217dbb41ff4a8d98ff3026a374dc2990.jpg", "method": "煮", "name": "大煮干丝"}
{"features": "", "labels": ["汤粥", "粤菜", "老年人", "晚餐"], "taste": "咸鲜味", "detail": "以前还住在老房子的时候，老妈就在家里的阳台上种了一颗霸王花，经过一年多的精心种植，霸王花长势非常强劲，接连不断地开花，每次老妈都把摘下来的花晒干，时不时地会煲上一锅霸王花的汤给全家大小喝，这霸王花有强身健体、清补养生的效果，并具有清热痰、除积热、止气痛、理痰火的功效。因此，霸王花煲汤具有清心润肺、清暑解热、除痰止咳的作用。霸王花的营养价值很高，是一种老少皆宜的花卉食材。", "image": "http://site.meishij.net/r/72/122/2343072/s2343072_70793.jpg", "method": "煲", "name": "霸王花煲猪骨"}
{"features": "", "labels": ["热菜", "粤菜", "老年人", "海鲜", "家常菜", "晚餐"], "taste": "家常味", "detail": "白灼虾，鲜虾最简单也是最美味的一种做法，白灼的烹饪工艺来自于粤菜，是将汤或水浇沸，下原料烫至刚熟捞出，称为‘灼’，因汤水中不加任何有色调味品，故叫白灼。", "image": "http://site.meishij.net/r/41/203/113291/s113291_59060.jpg", "method": "灼", "name": "白灼虾"}
